zsynctech_studio_sdk/__init__.py
zsynctech_studio_sdk/client.py
zsynctech_studio_sdk/context.py
zsynctech_studio_sdk/decorators.py
zsynctech_studio_sdk/decorators.pyi
zsynctech_studio_sdk/enums/__init__.py
zsynctech_studio_sdk/enums/execution.py
zsynctech_studio_sdk/enums/step.py
zsynctech_studio_sdk/enums/task.py
zsynctech_studio_sdk/logger.py
zsynctech_studio_sdk/models/__init__.py
zsynctech_studio_sdk/models/base.py
zsynctech_studio_sdk/models/config.py
zsynctech_studio_sdk/models/execution.py
zsynctech_studio_sdk/models/step.py
zsynctech_studio_sdk/models/task.py
zsynctech_studio_sdk/server.py
zsynctech_studio_sdk/storage.py
zsynctech_studio_sdk-1.2.0.dist-info/WHEEL
zsynctech_studio_sdk-1.2.0.dist-info/entry_points.txt
zsynctech_studio_sdk-1.2.0.dist-info/METADATA
zsynctech_studio_sdk-1.2.0.dist-info/RECORD
