Metadata-Version: 2.3
Name: zsynctech-studio-sdk
Version: 1.2.0
Summary: SDK Python para criação de robôs de automação com integração completa à plataforma ZSyncTech
Author: rodrigozavan
Author-email: rodrigozavan <rodrigozavan104@gmail.com>
Requires-Dist: pydantic>=2.0.0
Requires-Dist: uuid7>=0.1.0
Requires-Dist: fastapi>=0.115.0
Requires-Dist: uvicorn>=0.32.0
Requires-Dist: httpx>=0.27.0
Requires-Dist: cryptography>=43.0.0
Requires-Python: >=3.13
